robojob/__init__.py
robojob/backend.py
robojob/bcp.py
robojob/email.py
robojob/function.py
robojob/job_execution.py
robojob/parameter_collection.py
robojob/powershell.py
robojob/r.py
robojob/sql.py
robojob/task_execution.py
robojob/version.py
robojob-0.1.10.dist-info/METADATA
robojob-0.1.10.dist-info/WHEEL
robojob-0.1.10.dist-info/top_level.txt
robojob-0.1.10.dist-info/RECORD
